sqlalchemy_graphql_schemagen/__init__.py
sqlalchemy_graphql_schemagen/baseclasses/__init__.py
sqlalchemy_graphql_schemagen/baseclasses/logging.py
sqlalchemy_graphql_schemagen/graphql/__init__.py
sqlalchemy_graphql_schemagen/graphql/schemagen/__init__.py
sqlalchemy_graphql_schemagen/graphql/schemagen/extra.py
sqlalchemy_graphql_schemagen/graphql/schemagen/hooks.py
sqlalchemy_graphql_schemagen/graphql/schemagen/utilities.py
sqlalchemy_graphql_schemagen/sqlalchemy/__init__.py
sqlalchemy_graphql_schemagen/sqlalchemy/compositetypes/__init__.py
tests/__init__.py
sqlalchemy_graphql_schemagen-1.0.6.dist-info/LICENSE
sqlalchemy_graphql_schemagen-1.0.6.dist-info/METADATA
sqlalchemy_graphql_schemagen-1.0.6.dist-info/WHEEL
sqlalchemy_graphql_schemagen-1.0.6.dist-info/top_level.txt
sqlalchemy_graphql_schemagen-1.0.6.dist-info/RECORD
