Metadata-Version: 2.1
Name: sqlalchemy-graphql-schemagen
Version: 1.0.6
Summary: Generate a full (query+mutation) GraphQL schema from your SQLAlchemy Declarative Model Base.
Home-page: https://github.com/flipbit03/sqlalchemy-graphql-schemagen
Author: flipbit03
Author-email: cadu.coelho@gmail.com
License: MIT
Platform: UNKNOWN
Classifier: Programming Language :: Python :: 3
Classifier: License :: OSI Approved :: MIT License
Classifier: Operating System :: OS Independent
Requires-Python: >=3.7
License-File: LICENSE
Requires-Dist: cryptography (>=3.3.2)
Requires-Dist: flask (>=1.1.1)
Requires-Dist: flask-graphql (>=2.0.1)
Requires-Dist: graphene-sqlalchemy (>=2.2)
Requires-Dist: sqlalchemy (>=1.3.13)
